force_graph_panel/__init__.py
force_graph_panel/force_graph_component.py
force_graph_panel/multi_file_js_component_factory.py
force_graph_panel/recursive_js_component_factory.py
force_graph_panel/js/d3ForceGraph.js
force_graph_panel/js/d3ForceGraphAlt.js
force_graph_panel/js/d3ForceGraphOptions.js
force_graph_panel/js/d3ForceGraphPanel.js
force_graph_panel/js/forceGraphMessageHandler.js
force_graph_panel-0.0.1.dist-info/METADATA
force_graph_panel-0.0.1.dist-info/WHEEL
force_graph_panel-0.0.1.dist-info/top_level.txt
force_graph_panel-0.0.1.dist-info/RECORD
